README.md
setup.cfg
setup.py
gpflowopt/__init__.py
gpflowopt/_version.py
gpflowopt/bo.py
gpflowopt/design.py
gpflowopt/domain.py
gpflowopt/models.py
gpflowopt/objective.py
gpflowopt/optim.py
gpflowopt/pareto.py
gpflowopt/scaling.py
gpflowopt/transforms.py
gpflowopt.egg-info/PKG-INFO
gpflowopt.egg-info/SOURCES.txt
gpflowopt.egg-info/dependency_links.txt
gpflowopt.egg-info/requires.txt
gpflowopt.egg-info/top_level.txt
gpflowopt/acquisition/__init__.py
gpflowopt/acquisition/acquisition.py
gpflowopt/acquisition/ei.py
gpflowopt/acquisition/hvpoi.py
gpflowopt/acquisition/lcb.py
gpflowopt/acquisition/mes.py
gpflowopt/acquisition/pof.py
gpflowopt/acquisition/poi.py